LICENSE
startfile/__init__.py
startfile/__main__.py
python_startfile-0.0.2.dist-info/LICENSE
python_startfile-0.0.2.dist-info/METADATA
python_startfile-0.0.2.dist-info/WHEEL
python_startfile-0.0.2.dist-info/entry_points.txt
python_startfile-0.0.2.dist-info/RECORD
